byuhbll_configuro/__init__.py
byuhbll_configuro/core.py
byuhbll_configuro-1.0.0.dist-info/METADATA
byuhbll_configuro-1.0.0.dist-info/WHEEL
byuhbll_configuro-1.0.0.dist-info/licenses/LICENSE
byuhbll_configuro-1.0.0.dist-info/RECORD
