Metadata-Version: 2.4
Name: byuhbll-configuro
Version: 1.0.0
Summary: A configuration library for Python applications.
Project-URL: Homepage, https://gitlab.com/byuhbll/lib/python/configuro
Project-URL: Source, https://gitlab.com/byuhbll/lib/python/configuro
Author-email: BYU Library IT <byulibraryit@byu.edu>
License-Expression: BSD-3-Clause
License-File: LICENSE
Classifier: Intended Audience :: Developers
Classifier: Operating System :: OS Independent
Classifier: Programming Language :: Python
Classifier: Programming Language :: Python :: 3
Classifier: Programming Language :: Python :: 3 :: Only
Classifier: Programming Language :: Python :: 3.8
Classifier: Programming Language :: Python :: 3.9
Classifier: Programming Language :: Python :: 3.10
Classifier: Programming Language :: Python :: 3.11
Classifier: Programming Language :: Python :: 3.12
Classifier: Programming Language :: Python :: 3.13
Requires-Python: >=3.8
Requires-Dist: pyyaml
